zint.cpython-310-x86_64-linux-gnu.so
zint-stubs/__init__.pyi
zint_bindings-1.2.2.dist-info/METADATA
zint_bindings-1.2.2.dist-info/WHEEL
zint_bindings-1.2.2.dist-info/RECORD
zint_bindings-1.2.2.dist-info/licenses/LICENSE.md
