Metadata-Version: 2.2
Name: zint-bindings
Version: 1.2.2
Summary: A barcode encoding library supporting over 50 symbologies.
Keywords: QR,qrcode,datamatrix,barcode,generator,gs1,code128,aztec,pdf417,ean,code93,maxicode,microqr,rmqr
Author: Anna Zhukova
Classifier: Development Status :: 5 - Production/Stable
Classifier: License :: OSI Approved :: Apache Software License
Classifier: Natural Language :: English
Classifier: Operating System :: POSIX :: Linux
Classifier: Operating System :: Microsoft :: Windows
Classifier: Operating System :: MacOS
Classifier: Programming Language :: Python
Classifier: Programming Language :: Python :: 3.9
Classifier: Programming Language :: Python :: 3.10
Classifier: Programming Language :: Python :: 3.11
Classifier: Programming Language :: Python :: 3.12
Classifier: Programming Language :: Python :: 3.13
Classifier: Programming Language :: Python :: 3.14
Classifier: Programming Language :: Python :: Implementation :: CPython
Classifier: Programming Language :: Python :: Implementation :: PyPy
Classifier: Topic :: Communications
Classifier: Topic :: Multimedia :: Graphics
Project-URL: Documentation, https://zint-bindings.readthedocs.io/
Project-URL: Repository, https://github.com/bindreams/zint-bindings
Project-URL: Issues, https://github.com/bindreams/zint-bindings/issues
Requires-Python: >=3.9
Provides-Extra: test
Requires-Dist: pytest>=7; extra == "test"
Requires-Dist: pytest-sugar; extra == "test"
Requires-Dist: mypy; platform_python_implementation == "CPython" and extra == "test"
Provides-Extra: docs
Requires-Dist: sphinx; extra == "docs"
Requires-Dist: myst-parser; extra == "docs"
Requires-Dist: furo; extra == "docs"
Requires-Dist: sphinx-design; extra == "docs"
Requires-Dist: sphinx-copybutton; extra == "docs"
Requires-Dist: sphinx_substitution_extensions; extra == "docs"
